README.rst
setup.py
xenapi/XenAPI.py
xenapi/XenAPIPlugin.py
xenapi/__init__.py
xenapi_python.egg-info/PKG-INFO
xenapi_python.egg-info/SOURCES.txt
xenapi_python.egg-info/dependency_links.txt
xenapi_python.egg-info/requires.txt
xenapi_python.egg-info/top_level.txt