Metadata-Version: 1.1
Name: xenapi-python
Version: 1.127.1
Summary: Unofficial python bindings to XAPI (Xen API) for python 2 and 3
Home-page: https://github.com/salotz/xenapi-python
Author: Samuel D. Lotz
Author-email: samuel.lotz@salotz.info
License: MIT
Platform: UNKNOWN
Classifier: Development Status :: 2 - Pre-Alpha
Classifier: License :: OSI Approved :: MIT License
Classifier: Programming Language :: Python
Classifier: Programming Language :: Python :: 2
Classifier: Programming Language :: Python :: 2.7
Classifier: Programming Language :: Python :: 3
Classifier: Programming Language :: Python :: 3.4
Classifier: Programming Language :: Python :: 3.5
Classifier: Programming Language :: Python :: 3.6
Classifier: Programming Language :: Python :: 3.7
